nao_sql.py
nao_sql-2.2.8.dist-info/METADATA
nao_sql-2.2.8.dist-info/WHEEL
nao_sql-2.2.8.dist-info/top_level.txt
nao_sql-2.2.8.dist-info/RECORD
