Metadata-Version: 2.4
Name: nao_sql
Version: 2.2.8
Summary: The point of this package is to streamline the interaction of mssql databases in Python.
Author: Noah Harris
Classifier: Programming Language :: Python :: 3
Classifier: Operating System :: OS Independent
Requires-Python: >=3.11
Requires-Dist: requests>=2.24.0
Requires-Dist: pyodbc>=5.0.1
